prevcurrnext/__init__.py
prevcurrnext/__init__.pyi
prevcurrnext/py.typed
prevcurrnext-0.1.1.dist-info/LICENSE
prevcurrnext-0.1.1.dist-info/METADATA
prevcurrnext-0.1.1.dist-info/WHEEL
prevcurrnext-0.1.1.dist-info/RECORD
