Metadata-Version: 2.1
Name: prevcurrnext
Version: 0.1.1
Summary: Iteration utils for "prev", "curr", and "next"-style for-loops.
License: MIT
Author: J.I. Cruz
Author-email: hello@jicruz.com
Requires-Python: >=3.12,<4.0
Classifier: License :: OSI Approved :: MIT License
Classifier: Programming Language :: Python :: 3
Classifier: Programming Language :: Python :: 3.12
